py_fcm/__init__.py
py_fcm/fcm.py
py_fcm/fcm_estimator.py
py_fcm/loader.py
py_fcm/learning/__init__.py
py_fcm/learning/association.py
py_fcm/learning/utils.py
py_fcm/learning/discretization/__init__.py
py_fcm/learning/discretization/clusters_estimation.py
py_fcm/learning/discretization/fuzzy_cmeans.py
py_fcm/learning/discretization/rl_fuzzy_cmeans.py
py_fcm/utils/__const.py
py_fcm/utils/__init__.py
py_fcm/utils/functions.py
tests/__init__.py
tests/test_estimator.py
tests/test_fcm.py
tests/test_functions.py
tests/test_generator.py
tests/test_public_library_functions.py
py_fcm-1.0.0.dist-info/LICENSE
py_fcm-1.0.0.dist-info/METADATA
py_fcm-1.0.0.dist-info/WHEEL
py_fcm-1.0.0.dist-info/top_level.txt
py_fcm-1.0.0.dist-info/RECORD
