Metadata-Version: 2.1
Name: py-fcm
Version: 1.0.0
Summary: Fuzzy cognitive maps python library
Home-page: https://github.com/J41R0/PyFCM
Author: Jairo Lefebre
Author-email: jairo.lefebre@gmail.com
License: UNKNOWN
Platform: UNKNOWN
Classifier: Programming Language :: Python :: 3
Classifier: Operating System :: OS Independent
Requires-Python: >=3.7
Requires-Dist: pandas (>=0.24.2)
Requires-Dist: matplotlib (>=3.1.0)
Requires-Dist: networkx (>=2.3)
Requires-Dist: numpy (>=1.19.4)
Requires-Dist: numba (>=0.51.2)
